wsiPY/Classes.py
wsiPY/Demo.py
wsiPY/__init__.py
wsiPY/clusters.py
wsiPY/filters.py
wsiPY/folders.py
wsiPY/functions.py
wsiPY/test_folders.py
wsiPy-1.0.4.dist-info/LICENSE
wsiPy-1.0.4.dist-info/METADATA
wsiPy-1.0.4.dist-info/WHEEL
wsiPy-1.0.4.dist-info/top_level.txt
wsiPy-1.0.4.dist-info/RECORD
